{
"type": "FeatureCollection",
"name": "trips",
"crs": { "type": "name", "properties": { "name": "urn:ogc:def:crs:OGC:1.3:CRS84" } },
"features": [
{ "type": "Feature", "properties": { "id": null }, "geometry": { "type": "Point", "coordinates": [ 114.042192099217814, 22.530825799254831 ] } },
{ "type": "Feature", "properties": { "id": null }, "geometry": { "type": "Point", "coordinates": [ 114.048087551857591, 22.53141414915628 ] } },
{ "type": "Feature", "properties": { "id": null }, "geometry": { "type": "Point", "coordinates": [ 114.050457097022772, 22.530254493344991 ] } },
{ "type": "Feature", "properties": { "id": null }, "geometry": { "type": "Point", "coordinates": [ 114.051374300525396, 22.534269663922935 ] } },
{ "type": "Feature", "properties": { "id": null }, "geometry": { "type": "Point", "coordinates": [ 114.050237176637481, 22.537490331019249 ] } },
{ "type": "Feature", "properties": { "id": null }, "geometry": { "type": "Point", "coordinates": [ 114.044716748650771, 22.537863550640491 ] } },
{ "type": "Feature", "properties": { "id": null }, "geometry": { "type": "Point", "coordinates": [ 114.046725298091147, 22.542379323865038 ] } },
{ "type": "Feature", "properties": { "id": null }, "geometry": { "type": "Point", "coordinates": [ 114.056957680637467, 22.542526131019244 ] } },
{ "type": "Feature", "properties": { "id": null }, "geometry": { "type": "Point", "coordinates": [ 114.058074914718418, 22.537513356219687 ] } },
{ "type": "Feature", "properties": { "id": null }, "geometry": { "type": "Point", "coordinates": [ 114.058331080637473, 22.531227627019256 ] } },
{ "type": "Feature", "properties": { "id": null }, "geometry": { "type": "Point", "coordinates": [ 114.062977233476687, 22.529223325030639 ] } }
]
}
